engorgio/__about__.py
engorgio/__init__.py
engorgio/condense.py
engorgio/decorator.py
engorgio/expand.py
engorgio-0.4.0.dist-info/METADATA
engorgio-0.4.0.dist-info/WHEEL
engorgio-0.4.0.dist-info/licenses/LICENSE.txt
engorgio-0.4.0.dist-info/RECORD
