Metadata-Version: 2.1
Name: engorgio
Version: 0.4.0
Summary: Expand pydantic function arguments by casting the engorgio decorator
Project-URL: Documentation, https://github.com/waylonwalker/engorgio#readme
Project-URL: Issues, https://github.com/waylonwalker/engorgio/issues
Project-URL: Source, https://github.com/waylonwalker/engorgio
Project-URL: Changelog, https://github.com/WaylonWalker/engorgio/blob/main/CHANGELOG.md
Author-email: "Waylon S. Walker" <waylon@waylonwalker.com>
License-Expression: MIT
License-File: LICENSE.txt
Classifier: Development Status :: 4 - Beta
Classifier: Programming Language :: Python
Classifier: Programming Language :: Python :: 3.7
Classifier: Programming Language :: Python :: 3.8
Classifier: Programming Language :: Python :: 3.9
Classifier: Programming Language :: Python :: 3.10
Classifier: Programming Language :: Python :: 3.11
Classifier: Programming Language :: Python :: Implementation :: CPython
Classifier: Programming Language :: Python :: Implementation :: PyPy
Requires-Python: >=3.7
Requires-Dist: anyconfig
Requires-Dist: black
Requires-Dist: pydantic<2.0
Requires-Dist: rich
Requires-Dist: typer
